{
  "requestTime": "2024-12-18 19:35:00",
  "Central": {
    "WPG": {
      "gamesPlayed": 33,
      "wins": 23,
      "losses": 9,
      "otLosses": 1,
      "points": 47,
      "pointPctg": 0.712121
    },
    "MIN": {
      "gamesPlayed": 31,
      "wins": 20,
      "losses": 7,
      "otLosses": 4,
      "points": 44,
      "pointPctg": 0.709677
    },
    "DAL": {
      "gamesPlayed": 30,
      "wins": 19,
      "losses": 11,
      "otLosses": 0,
      "points": 38,
      "pointPctg": 0.633333
    }
  },
  "Pacific": {
    "VGK": {
      "gamesPlayed": 31,
      "wins": 20,
      "losses": 8,
      "otLosses": 3,
      "points": 43,
      "pointPctg": 0.693548
    },
    "LAK": {
      "gamesPlayed": 31,
      "wins": 18,
      "losses": 9,
      "otLosses": 4,
      "points": 40,
      "pointPctg": 0.645161
    },
    "EDM": {
      "gamesPlayed": 31,
      "wins": 18,
      "losses": 11,
      "otLosses": 2,
      "points": 38,
      "pointPctg": 0.612903
    }
  },
  "Atlantic": {
    "TOR": {
      "gamesPlayed": 31,
      "wins": 19,
      "losses": 10,
      "otLosses": 2,
      "points": 40,
      "pointPctg": 0.645161
    },
    "FLA": {
      "gamesPlayed": 32,
      "wins": 19,
      "losses": 11,
      "otLosses": 2,
      "points": 40,
      "pointPctg": 0.625
    },
    "BOS": {
      "gamesPlayed": 33,
      "wins": 17,
      "losses": 13,
      "otLosses": 3,
      "points": 37,
      "pointPctg": 0.560606
    }
  },
  "Metropolitan": {
    "NJD": {
      "gamesPlayed": 34,
      "wins": 21,
      "losses": 10,
      "otLosses": 3,
      "points": 45,
      "pointPctg": 0.661765
    },
    "WSH": {
      "gamesPlayed": 31,
      "wins": 21,
      "losses": 8,
      "otLosses": 2,
      "points": 44,
      "pointPctg": 0.709677
    },
    "CAR": {
      "gamesPlayed": 31,
      "wins": 20,
      "losses": 10,
      "otLosses": 1,
      "points": 41,
      "pointPctg": 0.66129
    }
  },
  "Western": {
    "VAN": {
      "gamesPlayed": 30,
      "wins": 16,
      "losses": 9,
      "otLosses": 5,
      "points": 37,
      "pointPctg": 0.616667
    },
    "CGY": {
      "gamesPlayed": 32,
      "wins": 15,
      "losses": 11,
      "otLosses": 6,
      "points": 36,
      "pointPctg": 0.5625
    },
    "COL": {
      "gamesPlayed": 33,
      "wins": 18,
      "losses": 15,
      "otLosses": 0,
      "points": 36,
      "pointPctg": 0.545455
    },
    "UTA": {
      "gamesPlayed": 30,
      "wins": 14,
      "losses": 11,
      "otLosses": 5,
      "points": 33,
      "pointPctg": 0.55
    },
    "STL": {
      "gamesPlayed": 33,
      "wins": 15,
      "losses": 15,
      "otLosses": 3,
      "points": 33,
      "pointPctg": 0.5
    },
    "SEA": {
      "gamesPlayed": 33,
      "wins": 15,
      "losses": 16,
      "otLosses": 2,
      "points": 32,
      "pointPctg": 0.484848
    },
    "SJS": {
      "gamesPlayed": 34,
      "wins": 11,
      "losses": 18,
      "otLosses": 5,
      "points": 27,
      "pointPctg": 0.397059
    },
    "ANA": {
      "gamesPlayed": 29,
      "wins": 11,
      "losses": 14,
      "otLosses": 4,
      "points": 26,
      "pointPctg": 0.448276
    },
    "CHI": {
      "gamesPlayed": 32,
      "wins": 11,
      "losses": 19,
      "otLosses": 2,
      "points": 24,
      "pointPctg": 0.375
    },
    "NSH": {
      "gamesPlayed": 32,
      "wins": 9,
      "losses": 17,
      "otLosses": 6,
      "points": 24,
      "pointPctg": 0.375
    }
  },
  "Eastern": {
    "TBL": {
      "gamesPlayed": 29,
      "wins": 17,
      "losses": 10,
      "otLosses": 2,
      "points": 36,
      "pointPctg": 0.62069
    },
    "OTT": {
      "gamesPlayed": 31,
      "wins": 16,
      "losses": 13,
      "otLosses": 2,
      "points": 34,
      "pointPctg": 0.548387
    },
    "PIT": {
      "gamesPlayed": 33,
      "wins": 14,
      "losses": 14,
      "otLosses": 5,
      "points": 33,
      "pointPctg": 0.5
    },
    "PHI": {
      "gamesPlayed": 31,
      "wins": 14,
      "losses": 13,
      "otLosses": 4,
      "points": 32,
      "pointPctg": 0.516129
    },
    "NYR": {
      "gamesPlayed": 31,
      "wins": 15,
      "losses": 15,
      "otLosses": 1,
      "points": 31,
      "pointPctg": 0.5
    },
    "NYI": {
      "gamesPlayed": 33,
      "wins": 12,
      "losses": 14,
      "otLosses": 7,
      "points": 31,
      "pointPctg": 0.469697
    },
    "CBJ": {
      "gamesPlayed": 32,
      "wins": 12,
      "losses": 15,
      "otLosses": 5,
      "points": 29,
      "pointPctg": 0.453125
    },
    "DET": {
      "gamesPlayed": 30,
      "wins": 12,
      "losses": 14,
      "otLosses": 4,
      "points": 28,
      "pointPctg": 0.466667
    },
    "MTL": {
      "gamesPlayed": 31,
      "wins": 12,
      "losses": 16,
      "otLosses": 3,
      "points": 27,
      "pointPctg": 0.435484
    },
    "BUF": {
      "gamesPlayed": 32,
      "wins": 11,
      "losses": 17,
      "otLosses": 4,
      "points": 26,
      "pointPctg": 0.40625
    }
  }
}